{
  "examSessions": [
    {
      "id": "2025_summer_session2",
      "name": "2025 (Летна) Втора испитна сесија",
      "year": "2025",
      "semester": "Летна",
      "session": "Втора испитна сесија"
    },
    {
      "id": "2025_summer_session1",
      "name": "2025 (Летна) Прва испитна сесија",
      "year": "2025",
      "semester": "Летна",
      "session": "Прва испитна сесија"
    },
    {
      "id": "2025_winter_session2",
      "name": "2025 (Зимска) Втора испитна сесија",
      "year": "2025",
      "semester": "Зимска",
      "session": "Втора испитна сесија"
    },
    {
      "id": "2025_winter_session1",
      "name": "2025 (Зимска) Прва испитна сесија",
      "year": "2025",
      "semester": "Зимска",
      "session": "Прва испитна сесија"
    },
    {
      "id": "2024_summer_session2",
      "name": "2024 (Летна) Втора испитна сесија",
      "year": "2024",
      "semester": "Летна",
      "session": "Втора испитна сесија"
    },
    {
      "id": "2024_summer_session1",
      "name": "2024 (Летна) Прва испитна сесија",
      "year": "2024",
      "semester": "Летна",
      "session": "Прва испитна сесија"
    },
    {
      "id": "2024_winter_session2",
      "name": "2024 (Зимска) Втора испитна сесија",
      "year": "2024",
      "semester": "Зимска",
      "session": "Втора испитна сесија"
    },
    {
      "id": "2024_winter_session1",
      "name": "2024 (Зимска) Прва испитна сесија",
      "year": "2024",
      "semester": "Зимска",
      "session": "Прва испитна сесија"
    }
  ],
  "currentSession": {
    "id": "2025_summer_session2",
    "name": "2025 (Летна) Втора испитна сесија"
  },
  "applications": [
    {
      "id": 1,
      "serviceNumber": "4684532",
      "code": "F23L2W014",
      "subject": "Компјутерски мрежи и безбедност",
      "completed": "Не",
      "fee": "0,00",
      "date": "21.05.2025",
      "instructor": "Сашо Граматиков",
      "decade": 1
    },
    {
      "id": 2,
      "serviceNumber": "4684531",
      "code": "F23L2W167",
      "subject": "Шаблони за дизајн на кориснички интерфејси",
      "completed": "Не",
      "fee": "0,00",
      "date": "21.05.2025",
      "instructor": "Сузана Лошковска",
      "decade": 1
    },
    {
      "id": 3,
      "serviceNumber": "4684530",
      "code": "F23L3S100",
      "subject": "Деловна пракса",
      "completed": "Не",
      "fee": "0,00",
      "date": "21.05.2025",
      "instructor": "Александар Стојменски",
      "decade": 1
    },
    {
      "id": 4,
      "serviceNumber": "4684529",
      "code": "F23L2S026",
      "subject": "Маркетинг",
      "completed": "Не",
      "fee": "0,00",
      "date": "21.05.2025",
      "instructor": "Билјана Стојкоска",
      "decade": 1
    },
    {
      "id": 5,
      "serviceNumber": "4684528",
      "code": "F23L2S017",
      "subject": "Оперативни системи",
      "completed": "Не",
      "fee": "0,00",
      "date": "21.05.2025",
      "instructor": "Невена Ацковска",
      "decade": 1
    },
    {
      "id": 6,
      "serviceNumber": "4684527",
      "code": "F23L2S029",
      "subject": "Софтверско инженерство",
      "completed": "Не",
      "fee": "0,00",
      "date": "21.05.2025",
      "instructor": "Ѓорѓи Маџаров",
      "decade": 1
    },
    {
      "id": 7,
      "serviceNumber": "4684526",
      "code": "F23L2S030",
      "subject": "Вештачка интелигенција",
      "completed": "Не",
      "fee": "0,00",
      "date": "21.05.2025",
      "instructor": "Соња Гиевска",
      "decade": 1
    }
  ],
  "note": "Серискиот број на електронската пријава задолжително треба да се впише на хартиената пријава која студентот ќе ја поднесе физички."
}